odoo8_addon_web_widget_digitized_signature-8.0.1.0.0.99.dev13-py2.7-nspkg.pth
odoo8_addon_web_widget_digitized_signature-8.0.1.0.0.99.dev13.dist-info/DESCRIPTION.rst
odoo8_addon_web_widget_digitized_signature-8.0.1.0.0.99.dev13.dist-info/METADATA
odoo8_addon_web_widget_digitized_signature-8.0.1.0.0.99.dev13.dist-info/RECORD
odoo8_addon_web_widget_digitized_signature-8.0.1.0.0.99.dev13.dist-info/WHEEL
odoo8_addon_web_widget_digitized_signature-8.0.1.0.0.99.dev13.dist-info/metadata.json
odoo8_addon_web_widget_digitized_signature-8.0.1.0.0.99.dev13.dist-info/namespace_packages.txt
odoo8_addon_web_widget_digitized_signature-8.0.1.0.0.99.dev13.dist-info/top_level.txt
odoo_addons/web_widget_digitized_signature/README.rst
odoo_addons/web_widget_digitized_signature/__init__.py
odoo_addons/web_widget_digitized_signature/__openerp__.py
odoo_addons/web_widget_digitized_signature/i18n/ar.po
odoo_addons/web_widget_digitized_signature/i18n/bg.po
odoo_addons/web_widget_digitized_signature/i18n/bs.po
odoo_addons/web_widget_digitized_signature/i18n/cs.po
odoo_addons/web_widget_digitized_signature/i18n/da.po
odoo_addons/web_widget_digitized_signature/i18n/de.po
odoo_addons/web_widget_digitized_signature/i18n/en_GB.po
odoo_addons/web_widget_digitized_signature/i18n/es.po
odoo_addons/web_widget_digitized_signature/i18n/es_AR.po
odoo_addons/web_widget_digitized_signature/i18n/es_CL.po
odoo_addons/web_widget_digitized_signature/i18n/es_CO.po
odoo_addons/web_widget_digitized_signature/i18n/es_CR.po
odoo_addons/web_widget_digitized_signature/i18n/es_DO.po
odoo_addons/web_widget_digitized_signature/i18n/es_EC.po
odoo_addons/web_widget_digitized_signature/i18n/es_MX.po
odoo_addons/web_widget_digitized_signature/i18n/es_PE.po
odoo_addons/web_widget_digitized_signature/i18n/es_PY.po
odoo_addons/web_widget_digitized_signature/i18n/es_VE.po
odoo_addons/web_widget_digitized_signature/i18n/et.po
odoo_addons/web_widget_digitized_signature/i18n/eu.po
odoo_addons/web_widget_digitized_signature/i18n/fa.po
odoo_addons/web_widget_digitized_signature/i18n/fi.po
odoo_addons/web_widget_digitized_signature/i18n/fr.po
odoo_addons/web_widget_digitized_signature/i18n/he.po
odoo_addons/web_widget_digitized_signature/i18n/hr.po
odoo_addons/web_widget_digitized_signature/i18n/hu.po
odoo_addons/web_widget_digitized_signature/i18n/id.po
odoo_addons/web_widget_digitized_signature/i18n/it.po
odoo_addons/web_widget_digitized_signature/i18n/ja.po
odoo_addons/web_widget_digitized_signature/i18n/ko.po
odoo_addons/web_widget_digitized_signature/i18n/lt.po
